dock8r/__init__.py
dock8r/cli.py
dock8r/docker.py
dock8r-0.1.3.dist-info/LICENSE
dock8r-0.1.3.dist-info/METADATA
dock8r-0.1.3.dist-info/WHEEL
dock8r-0.1.3.dist-info/entry_points.txt
dock8r-0.1.3.dist-info/top_level.txt
dock8r-0.1.3.dist-info/RECORD
