Metadata-Version: 2.1
Name: dock8r
Version: 0.1.3
Summary: CLI translating common Docker commands to run containers in K8s
Home-page: https://github.com/PolusAI/notebooks-hub
Author: Konstantin Taletskiy
Author-email: konstantin.taletskiy@labshare.org
License: MIT license
Keywords: docker
Classifier: Development Status :: 2 - Pre-Alpha
Classifier: Intended Audience :: Developers
Classifier: License :: OSI Approved :: MIT License
Classifier: Natural Language :: English
Classifier: Programming Language :: Python :: 3
Classifier: Programming Language :: Python :: 3.7
Classifier: Programming Language :: Python :: 3.8
Classifier: Programming Language :: Python :: 3.9
Requires-Python: >=3.6
License-File: LICENSE
Requires-Dist: Click (>=7.0)
Requires-Dist: randomname
Requires-Dist: kubernetes
Requires-Dist: escapism
Requires-Dist: humanfriendly
Requires-Dist: python-decouple
